SPTpython/CLI.py
SPTpython/MSDExplorer.py
SPTpython/SPTprocessing.py
SPTpython/SliderCombo.py
SPTpython/TIFViewer.py
SPTpython/__init__.py
SPTpython/colors.py
SPTpython/compare.py
SPTpython/config.py
SPTpython/constants.py
SPTpython/postprocessing.py
SPTpython/preprocessing.py
SPTpython/simulate.py
SPTpython/utils.py
SPTpython/version.py
SPTpython/C_code/__init__.py
SPTpython/C_code/kinetic_monte_carlo.c
SPTpython/C_code/kinetic_monte_carlo.h
SPTpython/C_code/kinetic_monte_carlo.pyx
SPTpython/C_code/kmc_impl.c
SPTpython/C_code/setup.py
SPTpython/C_code/test.py
SPTpython/C_code/test_kinetics.py
SPTpython/math/__init__.py
SPTpython/math/distribution_functions.py
SPTpython/scripts/CLIdriver.py
SPTpython/scripts/__init__.py
SPTpython/scripts/analyze_code.py
SPTpython/scripts/analyze_crossovers.py
SPTpython/scripts/analyze_emsds.py
SPTpython/scripts/analyze_simulation_xlinks.py
SPTpython/scripts/analyze_simulations.py
SPTpython/scripts/drive_simulation.py
SPTpython/scripts/microscope_usage.py
SPTpython/scripts/reduce_MLE.py
SPTpython/scripts/scratch.py
SPTpython/scripts/4th_year_review/comparison_config.py
SPTpython/scripts/4th_year_review/generate_html_4thyearreview.py
analysis/analyze_code.py
analysis/analyze_emsds.py
analysis/analyze_photobleach_kinetics.py
analysis/4th_year_review/generate_html_4thyearreview.py
resources/BUMPSDriver.py
resources/long delay/CLIdriver.py
resources/long delay/make_msd_figure.py
resources/long delay/microscope_usage.py
sptpython-1.0.4.dist-info/LICENSE
sptpython-1.0.4.dist-info/METADATA
sptpython-1.0.4.dist-info/WHEEL
sptpython-1.0.4.dist-info/entry_points.txt
sptpython-1.0.4.dist-info/top_level.txt
sptpython-1.0.4.dist-info/RECORD
